[
  {
    "productId": "SLD001",
    "productName": "Тунквана вафла",
    "description": "Хипер, Класик, 50 г",
    "promoPrice": 0.28,
    "regularPrice": 0.42,
    "discountPercentage": 34,
    "validFrom": "12.03.2026",
    "validTo": "18.03.2026",
    "loyaltyCard": false,
    "notes": ""
  },
  {
    "productId": "SLD002",
    "productName": "Бонбони Chocolateria",
    "description": "Roshen, Gift Selection, 194 г",
    "promoPrice": 3.57,
    "regularPrice": 6.05,
    "discountPercentage": 41,
    "validFrom": "12.03.2026",
    "validTo": "18.03.2026",
    "loyaltyCard": false,
    "notes": ""
  },
  {
    "productId": "SLD003",
    "productName": "Бонбониера Lindor",
    "description": "Lindt, 337 г",
    "promoPrice": 7.15,
    "regularPrice": 12.12,
    "discountPercentage": 41,
    "validFrom": "12.03.2026",
    "validTo": "18.03.2026",
    "loyaltyCard": false,
    "notes": ""
  },
  {
    "productId": "SLD004",
    "productName": "Пудинг",
    "description": "Clever, различни видове, 200 г",
    "promoPrice": 0.54,
    "regularPrice": 0.54,
    "discountPercentage": 0,
    "validFrom": "12.03.2026",
    "validTo": "18.03.2026",
    "loyaltyCard": false,
    "notes": ""
  },
  {
    "productId": "SLD005",
    "productName": "Десерт с глазура",
    "description": "BILLA Cocoa Snack, 6 x 30 г",
    "promoPrice": 1.99,
    "regularPrice": 2.52,
    "discountPercentage": 21,
    "validFrom": "12.03.2026",
    "validTo": "18.03.2026",
    "loyaltyCard": false,
    "notes": ""
  },
  {
    "productId": "SLD006",
    "productName": "Донът ягода",
    "description": "56 г",
    "promoPrice": 0.46,
    "regularPrice": 0.61,
    "discountPercentage": 24,
    "validFrom": "12.03.2026",
    "validTo": "18.03.2026",
    "loyaltyCard": false,
    "notes": ""
  },
  {
    "productId": "SLD007",
    "productName": "Сладоледи (всички)",
    "description": "BILLA и BILLA Premium",
    "promoPrice": null,
    "regularPrice": null,
    "discountPercentage": 40,
    "validFrom": "12.03.2026",
    "validTo": "18.03.2026",
    "loyaltyCard": true,
    "notes": "Промоцията изисква BILLA Card."
  },
  {
    "productId": "SLD008",
    "productName": "Млечно-кисел десерт",
    "description": "БАЛКАН, 200 г",
    "promoPrice": 0.69,
    "regularPrice": 1.01,
    "discountPercentage": 32,
    "validFrom": "12.03.2026",
    "validTo": "18.03.2026",
    "loyaltyCard": false,
    "notes": ""
  },
  {
    "productId": "SLD009",
    "productName": "Кремове и пудинги",
    "description": "JOTIS, всички видове",
    "promoPrice": null,
    "regularPrice": null,
    "discountPercentage": 25,
    "validFrom": "12.03.2026",
    "validTo": "18.03.2026",
    "loyaltyCard": true,
    "notes": "Промоцията изисква BILLA Card."
  },
  {
    "productId": "SLD010",
    "productName": "Лешников и какаов крем",
    "description": "Nocciolata, био, 250 г",
    "promoPrice": null,
    "regularPrice": null,
    "discountPercentage": 20,
    "validFrom": "12.03.2026",
    "validTo": "18.03.2026",
    "loyaltyCard": true,
    "notes": "Промоцията изисква BILLA Card."
  },
  {
    "productId": "SLD011",
    "productName": "Протеинов бар Дубайски стил",
    "description": "Fit Spo, 50 г",
    "promoPrice": 1.17,
    "regularPrice": 2.02,
    "discountPercentage": 42,
    "validFrom": "12.03.2026",
    "validTo": "18.03.2026",
    "loyaltyCard": false,
    "notes": ""
  },
  {
    "productId": "SLD012",
    "productName": "Протеинов бар Кокос",
    "description": "Oshee, 48 г",
    "promoPrice": 1.53,
    "regularPrice": 2.28,
    "discountPercentage": 33,
    "validFrom": "12.03.2026",
    "validTo": "18.03.2026",
    "loyaltyCard": false,
    "notes": ""
  },
  {
    "productId": "SLD013",
    "productName": "Протеинова вафла",
    "description": "Brain Foods, 40 г",
    "promoPrice": 1.53,
    "regularPrice": 2.28,
    "discountPercentage": 33,
    "validFrom": "12.03.2026",
    "validTo": "18.03.2026",
    "loyaltyCard": false,
    "notes": ""
  },
  {
    "productId": "SLD014",
    "productName": "Протеинов мъфин",
    "description": "MHN Delicious, 50 г",
    "promoPrice": 1.53,
    "regularPrice": 2.28,
    "discountPercentage": 33,
    "validFrom": "12.03.2026",
    "validTo": "18.03.2026",
    "loyaltyCard": false,
    "notes": ""
  },
  {
    "productId": "SLD015",
    "productName": "Протеинов бар Солен карамел",
    "description": "Fit Spo Pro, 85 г",
    "promoPrice": 1.59,
    "regularPrice": 2.09,
    "discountPercentage": 24,
    "validFrom": "12.03.2026",
    "validTo": "18.03.2026",
    "loyaltyCard": false,
    "notes": ""
  },
  {
    "productId": "SLD016",
    "productName": "Протеинови чашки",
    "description": "Born Winner, 2 х 25 г",
    "promoPrice": 2.04,
    "regularPrice": 2.83,
    "discountPercentage": 28,
    "validFrom": "12.03.2026",
    "validTo": "18.03.2026",
    "loyaltyCard": false,
    "notes": ""
  },
  {
    "productId": "SLD017",
    "productName": "Протеинов бар Кокос/Чийзкейк",
    "description": "Born Winner, 2 х 30 г",
    "promoPrice": 1.38,
    "regularPrice": 1.64,
    "discountPercentage": 16,
    "validFrom": "12.03.2026",
    "validTo": "18.03.2026",
    "loyaltyCard": false,
    "notes": ""
  },
  {
    "productId": "SLD018",
    "productName": "Протеинов бар Deluxe",
    "description": "Born Winner, 57 г",
    "promoPrice": 2.3,
    "regularPrice": 3.43,
    "discountPercentage": 33,
    "validFrom": "12.03.2026",
    "validTo": "18.03.2026",
    "loyaltyCard": false,
    "notes": ""
  },
  {
    "productId": "SLD019",
    "productName": "Кроасан",
    "description": "Belino, 80 г",
    "promoPrice": 0.45,
    "regularPrice": 0.61,
    "discountPercentage": 26,
    "validFrom": "12.03.2026",
    "validTo": "18.03.2026",
    "loyaltyCard": false,
    "notes": ""
  },
  {
    "productId": "SLD020",
    "productName": "Желирани бонбони",
    "description": "Roshen Bonny Fruit, 200 г",
    "promoPrice": 0.89,
    "regularPrice": 1.22,
    "discountPercentage": 27,
    "validFrom": "12.03.2026",
    "validTo": "18.03.2026",
    "loyaltyCard": false,
    "notes": ""
  },
  {
    "productId": "SLD021",
    "productName": "Насипни бонбони",
    "description": "1 кг",
    "promoPrice": 6.99,
    "regularPrice": 9.58,
    "discountPercentage": 27,
    "validFrom": "12.03.2026",
    "validTo": "18.03.2026",
    "loyaltyCard": false,
    "notes": ""
  },
  {
    "productId": "SLD022",
    "productName": "Шоколадов десерт 2 pack",
    "description": "Lion, 60 г",
    "promoPrice": 0.76,
    "regularPrice": 1.12,
    "discountPercentage": 32,
    "validFrom": "12.03.2026",
    "validTo": "18.03.2026",
    "loyaltyCard": false,
    "notes": ""
  },
  {
    "productId": "SLD023",
    "productName": "Шоколад Lacmi",
    "description": "260–295 г",
    "promoPrice": 2.99,
    "regularPrice": 2.99,
    "discountPercentage": 0,
    "validFrom": "12.03.2026",
    "validTo": "18.03.2026",
    "loyaltyCard": false,
    "notes": ""
  },
  {
    "productId": "SLD024",
    "productName": "Суха паста Мини кейк",
    "description": "Престиж, 50 г",
    "promoPrice": 0.25,
    "regularPrice": 0.4,
    "discountPercentage": 37,
    "validFrom": "12.03.2026",
    "validTo": "18.03.2026",
    "loyaltyCard": false,
    "notes": ""
  },
  {
    "productId": "SLD025",
    "productName": "Обикновени бисквити",
    "description": "Житен Дар, 220 г",
    "promoPrice": 1.02,
    "regularPrice": 1.24,
    "discountPercentage": 18,
    "validFrom": "12.03.2026",
    "validTo": "18.03.2026",
    "loyaltyCard": false,
    "notes": ""
  },
  {
    "productId": "SLD026",
    "productName": "Бисквити Oreo",
    "description": "154 г",
    "promoPrice": 1.38,
    "regularPrice": 1.92,
    "discountPercentage": 28,
    "validFrom": "12.03.2026",
    "validTo": "18.03.2026",
    "loyaltyCard": false,
    "notes": ""
  },
  {
    "productId": "SLD027",
    "productName": "Пурички Caprice",
    "description": "400 г",
    "promoPrice": 4.34,
    "regularPrice": 6.03,
    "discountPercentage": 28,
    "validFrom": "12.03.2026",
    "validTo": "18.03.2026",
    "loyaltyCard": false,
    "notes": ""
  },
  {
    "productId": "SLD028",
    "productName": "Тунквани бисквити",
    "description": "Боровец, карамел и фъстъци, 180 г",
    "promoPrice": 1.38,
    "regularPrice": 1.72,
    "discountPercentage": 20,
    "validFrom": "12.03.2026",
    "validTo": "18.03.2026",
    "loyaltyCard": false,
    "notes": ""
  },
  {
    "productId": "SLD029",
    "productName": "Нетунквани вафли Ная",
    "description": "Престиж, 350 г",
    "promoPrice": 1.68,
    "regularPrice": 2.27,
    "discountPercentage": 26,
    "validFrom": "12.03.2026",
    "validTo": "18.03.2026",
    "loyaltyCard": false,
    "notes": ""
  },
  {
    "productId": "SLD030",
    "productName": "Бисквити Soft Cookies",
    "description": "BILLA Premium, 210 г",
    "promoPrice": 2.45,
    "regularPrice": 3.02,
    "discountPercentage": 19,
    "validFrom": "12.03.2026",
    "validTo": "18.03.2026",
    "loyaltyCard": false,
    "notes": ""
  },
  {
    "productId": "SLD031",
    "productName": "Течен шоколад",
    "description": "Nutella, 400 г",
    "promoPrice": 4.09,
    "regularPrice": 5.05,
    "discountPercentage": 19,
    "validFrom": "12.03.2026",
    "validTo": "18.03.2026",
    "loyaltyCard": false,
    "notes": ""
  },
  {
    "productId": "SLD032",
    "productName": "Пчелен мед от акация",
    "description": "Булмед, 900 г",
    "promoPrice": 6.19,
    "regularPrice": 7.74,
    "discountPercentage": 20,
    "validFrom": "12.03.2026",
    "validTo": "18.03.2026",
    "loyaltyCard": true,
    "notes": "Промоцията изисква BILLA Card."
  },
  {
    "productId": "SLD033",
    "productName": "Тунквани бисквити",
    "description": "Престиж, 300 г",
    "promoPrice": 1.78,
    "regularPrice": 2.54,
    "discountPercentage": 30,
    "validFrom": "12.03.2026",
    "validTo": "18.03.2026",
    "loyaltyCard": true,
    "notes": "Промоцията изисква BILLA Card."
  },
  {
    "productId": "SLD034",
    "productName": "Digestive бар",
    "description": "28 г",
    "promoPrice": 0.01,
    "regularPrice": 0.01,
    "discountPercentage": 0,
    "validFrom": "01.03.2026",
    "validTo": "31.03.2026",
    "loyaltyCard": false,
    "notes": "условия"
  },
  {
    "productId": "SLD035",
    "productName": "Шоколад (млечен или Oreo)",
    "description": "Milka, 90–100 г",
    "promoPrice": 0.95,
    "regularPrice": 2.44,
    "discountPercentage": 61,
    "validFrom": "16.03.2026",
    "validTo": "18.03.2026",
    "loyaltyCard": false,
    "notes": ""
  },
  {
    "productId": "SLD036",
    "productName": "Всички шоколади (акция)",
    "description": "Различни марки",
    "promoPrice": null,
    "regularPrice": null,
    "discountPercentage": 25,
    "validFrom": "13.03.2026",
    "validTo": "15.03.2026",
    "loyaltyCard": true,
    "notes": "Промоцията изисква BILLA Card."
  },
  {
    "productId": "SLD039",
    "productName": "Протеинов бар крънч шоколад",
    "description": "fit spo",
    "promoPrice": 1.55,
    "regularPrice": 1.55,
    "discountPercentage": 0,
    "validFrom": "",
    "validTo": "",
    "loyaltyCard": false,
    "notes": ""
  }
]